textpress/__init__.py
textpress/__main__.py
textpress/py.typed
textpress/actions/__init__.py
textpress/actions/textpress_export.py
textpress/actions/textpress_format.py
textpress/actions/textpress_publish.py
textpress/actions/textpress_render_template.py
textpress/api/__init__.py
textpress/api/http_client.py
textpress/api/textpress_api.py
textpress/api/textpress_env.py
textpress/cli/__init__.py
textpress/cli/cli_commands.py
textpress/cli/cli_docs.py
textpress/cli/cli_main.py
textpress/cli/cli_setup.py
textpress/docs/__init__.py
textpress/docs/render_webpage.py
textpress/docs/templates/textpress_webpage.html.jinja
textpress-0.1.2.dist-info/METADATA
textpress-0.1.2.dist-info/WHEEL
textpress-0.1.2.dist-info/entry_points.txt
textpress-0.1.2.dist-info/licenses/LICENSE
textpress-0.1.2.dist-info/RECORD
